ncssl_api_client/__init__.py
ncssl_api_client/__main__.py
ncssl_api_client/configure.py
ncssl_api_client/api/__init__.py
ncssl_api_client/api/api_client.py
ncssl_api_client/api/api_exception.py
ncssl_api_client/api/api_response.py
ncssl_api_client/api/commands/__init__.py
ncssl_api_client/api/commands/abstract_command.py
ncssl_api_client/api/commands/activate_command.py
ncssl_api_client/api/commands/create_command.py
ncssl_api_client/api/commands/get_email_list_command.py
ncssl_api_client/api/commands/get_info_command.py
ncssl_api_client/api/commands/getlist_command.py
ncssl_api_client/api/commands/invoker.py
ncssl_api_client/api/commands/reissue_command.py
ncssl_api_client/api/commands/renew_command.py
ncssl_api_client/api/commands/retry_dcv_command.py
ncssl_api_client/api/commands/revoke_command.py
ncssl_api_client/api/enumerables/__init__.py
ncssl_api_client/api/enumerables/certificate_types.py
ncssl_api_client/api/enumerables/filters.py
ncssl_api_client/api/enumerables/sorters.py
ncssl_api_client/config/__init__.py
ncssl_api_client/config/manager.py
ncssl_api_client/config/api/__init__.py
ncssl_api_client/config/api/abstract_api_client_config.py
ncssl_api_client/config/api/api_client_production_config.py
ncssl_api_client/config/api/api_client_sandbox_config.py
ncssl_api_client/config/api/api_command_config.py
ncssl_api_client/config/api/settings.py
ncssl_api_client/config/api/settings.yaml
ncssl_api_client/config/crypto/__init__.py
ncssl_api_client/config/crypto/crypto_config.py
ncssl_api_client/config/crypto/settings.py
ncssl_api_client/config/crypto/settings.yaml
ncssl_api_client/console/__init__.py
ncssl_api_client/console/parsers/__init__.py
ncssl_api_client/console/parsers/abstract_parser.py
ncssl_api_client/console/parsers/activate_parser.py
ncssl_api_client/console/parsers/create_parser.py
ncssl_api_client/console/parsers/get_email_list_parser.py
ncssl_api_client/console/parsers/get_list_parser.py
ncssl_api_client-1.0.2.dist-info/DESCRIPTION.rst
ncssl_api_client-1.0.2.dist-info/METADATA
ncssl_api_client-1.0.2.dist-info/RECORD
ncssl_api_client-1.0.2.dist-info/WHEEL
ncssl_api_client-1.0.2.dist-info/entry_points.txt
ncssl_api_client-1.0.2.dist-info/metadata.json
ncssl_api_client-1.0.2.dist-info/top_level.txt
