Metadata-Version: 2.0
Name: ncssl-api-client
Version: 1.0.2
Summary: Command line interface for Namecheap SSL API
Home-page: https://github.com/antonku/ncssl_api_client
Author: Anton Kudinov
Author-email: anton.ku.nc@gmail.com
License: MIT
Platform: UNKNOWN
Classifier: Development Status :: 5 - Production/Stable
Classifier: Environment :: Console
Classifier: Intended Audience :: Developers
Classifier: Intended Audience :: System Administrators
Classifier: Operating System :: MacOS :: MacOS X
Classifier: Operating System :: POSIX
Classifier: Programming Language :: Python
Classifier: License :: OSI Approved :: MIT License
Requires-Dist: coloredlogs
Requires-Dist: enum34
Requires-Dist: future
Requires-Dist: mock
Requires-Dist: pyyaml
Requires-Dist: requests
Requires-Dist: xmltodict
